{"path":null,"code":"10000","msg":"请求成功","body":{"data":{"processDetail":"{\"release_id\":\"598\",\"process_log\":[{\"F_process_user\":\"wangqin_dxm\",\"F_state\":\"3\",\"F_create_time\":\"2019-04-12 18:30:32\",\"F_serial_no\":\"0\",\"F_modify_time\":\"2019-04-12 18:30:32\",\"F_remark\":\"\",\"F_id\":\"4799\",\"F_prodb_id\":\"14053\",\"F_process_type\":\"1\",\"F_type\":\"2\",\"F_trans_user\":\"\",\"F_enabled\":\"1\",\"F_step_id\":\"23\",\"F_process_id\":\"1316\"}],\"audit\":[{\"role\":\"23\",\"audit_state\":\"3\",\"role_info\":\"数据申请者经理\",\"name\":\"wangqin_dxm\",\"remark\":\"\",\"state\":\"1\",\"id\":\"14053\",\"step_id\":\"23\",\"steps\":\"23\"},{\"role\":\"35\",\"audit_state\":\"1\",\"role_info\":\"业务审核人员\",\"name\":\"yanyuelei_dxm\",\"remark\":\"\",\"state\":\"1\",\"id\":\"14054\",\"step_id\":\"806\",\"steps\":\"806\",\"is_now\":1},{\"role\":\"33\",\"audit_state\":1,\"role_info\":\"安全审核人员\",\"name\":\"lihongbin_dxm\",\"state\":\"1\",\"steps\":\"804\"},{\"role\":\"33\",\"audit_state\":1,\"role_info\":\"安全审核人员\",\"name\":\"zhongping_dxm\",\"state\":\"1\",\"steps\":\"804\"},{\"role\":\"33\",\"audit_state\":1,\"role_info\":\"安全审核人员\",\"name\":\"sunqifeng_dxm\",\"state\":\"1\",\"steps\":\"804\"},{\"role\":\"33\",\"audit_state\":1,\"role_info\":\"安全审核人员\",\"name\":\"wuqiongfang_dxm\",\"state\":\"1\",\"steps\":\"804\"},{\"role\":\"33\",\"audit_state\":1,\"role_info\":\"安全审核人员\",\"name\":\"zhangwei01_dxm\",\"state\":\"1\",\"steps\":\"804\"},{\"role\":\"33\",\"audit_state\":1,\"role_info\":\"安全审核人员\",\"name\":\"yangyang_dxm\",\"state\":\"1\",\"steps\":\"804\"}],\"process_state\":\"2\",\"release_type\":\"1\",\"task_id\":\"\"}","operatorList":[],"manageInfoDetail":{"id":20,"fdwTable":"prom_user_sms_event","fdwDetail":"数据来源于客户经营的短信营销表；每日全量更新","fdwTitle":"现金贷用户营销短信事件","fdwApplyType":2,"fdwAvailableTime":"186","fdwRemark":"","fdwReleaseId":1316,"fdwBackground":"全链路评估用户体验，从全链路角度梳理各节点的短信触达及触达策略问题。","fdwExpect":"提高全链路用户体验","fdwUseMode":"{\"label\":\"拖走数据在本地办公环境存储\",\"value\":\"3\"}","fdwUseEnv":"用户体验部-用户研究","fdwLsoName":"","fdwGroupName":"fsg_rcc_loan_productmgt_uer","fdwUseType":"{\"label\":\"线下调研分析\",\"value\":\"4\"}","fdwCreateTime":1555062733000,"fdwModifyTime":1555062733000,"status":1,"createTime":1555062733000,"updateTime":1555071238230,"applyUser":"wangtong_dxm","publishId":78,"fdwDataFields":"[{\"name\":\"bid\",\"type\":\"bigint\",\"level\":\"13\",\"is_null\":\"1\",\"is_mask\":\"0\",\"detail\":\"bid\",\"remark\":\"\",\"remarkCode\":\"1\",\"customerType\":\"BID\"},{\"name\":\"content\",\"type\":\"string\",\"level\":\"13\",\"is_null\":\"1\",\"is_mask\":\"0\",\"detail\":\"发送内容\",\"remark\":\"\",\"remarkCode\":\"0\",\"customerType\":null},{\"name\":\"deliver_state\",\"type\":\"smallint\",\"level\":\"13\",\"is_null\":\"1\",\"is_mask\":\"0\",\"detail\":\"发送是否成功\",\"remark\":\"\",\"remarkCode\":\"0\",\"customerType\":null},{\"name\":\"dt\",\"type\":\"string\",\"level\":\"13\",\"is_null\":\"1\",\"is_mask\":\"0\",\"detail\":\"事件发生日期，yyyy-MM-dd格式\",\"remark\":\"\",\"remarkCode\":\"0\",\"customerType\":null},{\"name\":\"event_time\",\"type\":\"bigint\",\"level\":\"13\",\"is_null\":\"1\",\"is_mask\":\"0\",\"detail\":\"事件发生的时间戳\",\"remark\":\"\",\"remarkCode\":\"0\",\"customerType\":null},{\"name\":\"product_code\",\"type\":\"string\",\"level\":\"13\",\"is_null\":\"1\",\"is_mask\":\"0\",\"detail\":\"归属业务产品\",\"remark\":\"\",\"remarkCode\":\"0\",\"customerType\":null},{\"name\":\"request_id\",\"type\":\"string\",\"level\":\"13\",\"is_null\":\"1\",\"is_mask\":\"0\",\"detail\":\"事件编码\",\"remark\":\"\",\"remarkCode\":\"0\",\"customerType\":null},{\"name\":\"send_platform\",\"type\":\"string\",\"level\":\"13\",\"is_null\":\"1\",\"is_mask\":\"0\",\"detail\":\"策略触发平台（1：伯乐，2：客户经营）\",\"remark\":\"\",\"remarkCode\":\"0\",\"customerType\":null},{\"name\":\"sms_type\",\"type\":\"smallint\",\"level\":\"13\",\"is_null\":\"1\",\"is_mask\":\"0\",\"detail\":\"短信类型（0:验证码短信1:通知类型短信2:营销类型短信）\",\"remark\":\"\",\"remarkCode\":\"0\",\"customerType\":null},{\"name\":\"strategy_code\",\"type\":\"string\",\"level\":\"13\",\"is_null\":\"1\",\"is_mask\":\"0\",\"detail\":\"策略编码\",\"remark\":\"\",\"remarkCode\":\"0\",\"customerType\":null},{\"name\":\"strategy_id\",\"type\":\"bigint\",\"level\":\"13\",\"is_null\":\"1\",\"is_mask\":\"0\",\"detail\":\"策略id\",\"remark\":\"\",\"remarkCode\":\"0\",\"customerType\":null},{\"name\":\"strategy_name\",\"type\":\"string\",\"level\":\"13\",\"is_null\":\"1\",\"is_mask\":\"0\",\"detail\":\"策略名称\",\"remark\":\"\",\"remarkCode\":\"0\",\"customerType\":null},{\"name\":\"url\",\"type\":\"string\",\"level\":\"13\",\"is_null\":\"1\",\"is_mask\":\"0\",\"detail\":\"关联url（保留字段，暂无数据）\",\"remark\":\"\",\"remarkCode\":\"0\",\"customerType\":null},{\"name\":\"user_phone\",\"type\":\"string\",\"level\":\"15\",\"is_null\":\"1\",\"is_mask\":\"0\",\"detail\":\"发送手机号（保留字段，暂无数据）\",\"remark\":\"\",\"remarkCode\":\"0\",\"customerType\":null}]","applyFields":"[{\"name\":\"bid\",\"type\":\"bigint\",\"level\":\"13\",\"is_null\":\"1\",\"is_mask\":\"0\",\"detail\":\"bid\",\"remark\":\"\",\"remarkCode\":\"1\",\"customerType\":\"BID\"},{\"name\":\"content\",\"type\":\"string\",\"level\":\"13\",\"is_null\":\"1\",\"is_mask\":\"0\",\"detail\":\"发送内容\",\"remark\":\"\",\"remarkCode\":\"0\",\"customerType\":null},{\"name\":\"deliver_state\",\"type\":\"smallint\",\"level\":\"13\",\"is_null\":\"1\",\"is_mask\":\"0\",\"detail\":\"发送是否成功\",\"remark\":\"\",\"remarkCode\":\"0\",\"customerType\":null},{\"name\":\"dt\",\"type\":\"string\",\"level\":\"13\",\"is_null\":\"1\",\"is_mask\":\"0\",\"detail\":\"事件发生日期，yyyy-MM-dd格式\",\"remark\":\"\",\"remarkCode\":\"0\",\"customerType\":null},{\"name\":\"event_time\",\"type\":\"bigint\",\"level\":\"13\",\"is_null\":\"1\",\"is_mask\":\"0\",\"detail\":\"事件发生的时间戳\",\"remark\":\"\",\"remarkCode\":\"0\",\"customerType\":null},{\"name\":\"product_code\",\"type\":\"string\",\"level\":\"13\",\"is_null\":\"1\",\"is_mask\":\"0\",\"detail\":\"归属业务产品\",\"remark\":\"\",\"remarkCode\":\"0\",\"customerType\":null},{\"name\":\"request_id\",\"type\":\"string\",\"level\":\"13\",\"is_null\":\"1\",\"is_mask\":\"0\",\"detail\":\"事件编码\",\"remark\":\"\",\"remarkCode\":\"0\",\"customerType\":null},{\"name\":\"send_platform\",\"type\":\"string\",\"level\":\"13\",\"is_null\":\"1\",\"is_mask\":\"0\",\"detail\":\"策略触发平台（1：伯乐，2：客户经营）\",\"remark\":\"\",\"remarkCode\":\"0\",\"customerType\":null},{\"name\":\"sms_type\",\"type\":\"smallint\",\"level\":\"13\",\"is_null\":\"1\",\"is_mask\":\"0\",\"detail\":\"短信类型（0:验证码短信1:通知类型短信2:营销类型短信）\",\"remark\":\"\",\"remarkCode\":\"0\",\"customerType\":null},{\"name\":\"strategy_code\",\"type\":\"string\",\"level\":\"13\",\"is_null\":\"1\",\"is_mask\":\"0\",\"detail\":\"策略编码\",\"remark\":\"\",\"remarkCode\":\"0\",\"customerType\":null},{\"name\":\"strategy_id\",\"type\":\"bigint\",\"level\":\"13\",\"is_null\":\"1\",\"is_mask\":\"0\",\"detail\":\"策略id\",\"remark\":\"\",\"remarkCode\":\"0\",\"customerType\":null},{\"name\":\"strategy_name\",\"type\":\"string\",\"level\":\"13\",\"is_null\":\"1\",\"is_mask\":\"0\",\"detail\":\"策略名称\",\"remark\":\"\",\"remarkCode\":\"0\",\"customerType\":null},{\"name\":\"url\",\"type\":\"string\",\"level\":\"13\",\"is_null\":\"1\",\"is_mask\":\"0\",\"detail\":\"关联url（保留字段，暂无数据）\",\"remark\":\"\",\"remarkCode\":\"0\",\"customerType\":null},{\"name\":\"user_phone\",\"type\":\"string\",\"level\":\"15\",\"is_null\":\"1\",\"is_mask\":\"0\",\"detail\":\"发送手机号（保留字段，暂无数据）\",\"remark\":\"\",\"remarkCode\":\"0\",\"customerType\":null}]","processInfo":"{\"release_id\":\"598\",\"process_log\":[{\"F_process_user\":\"wangqin_dxm\",\"F_state\":\"3\",\"F_create_time\":\"2019-04-12 18:30:32\",\"F_serial_no\":\"0\",\"F_modify_time\":\"2019-04-12 18:30:32\",\"F_remark\":\"\",\"F_id\":\"4799\",\"F_prodb_id\":\"14053\",\"F_process_type\":\"1\",\"F_type\":\"2\",\"F_trans_user\":\"\",\"F_enabled\":\"1\",\"F_step_id\":\"23\",\"F_process_id\":\"1316\"}],\"audit\":[{\"role\":\"23\",\"audit_state\":\"3\",\"role_info\":\"数据申请者经理\",\"name\":\"wangqin_dxm\",\"remark\":\"\",\"state\":\"1\",\"id\":\"14053\",\"step_id\":\"23\",\"steps\":\"23\"},{\"role\":\"35\",\"audit_state\":\"1\",\"role_info\":\"业务审核人员\",\"name\":\"yanyuelei_dxm\",\"remark\":\"\",\"state\":\"1\",\"id\":\"14054\",\"step_id\":\"806\",\"steps\":\"806\",\"is_now\":1},{\"role\":\"33\",\"audit_state\":1,\"role_info\":\"安全审核人员\",\"name\":\"lihongbin_dxm\",\"state\":\"1\",\"steps\":\"804\"},{\"role\":\"33\",\"audit_state\":1,\"role_info\":\"安全审核人员\",\"name\":\"zhongping_dxm\",\"state\":\"1\",\"steps\":\"804\"},{\"role\":\"33\",\"audit_state\":1,\"role_info\":\"安全审核人员\",\"name\":\"sunqifeng_dxm\",\"state\":\"1\",\"steps\":\"804\"},{\"role\":\"33\",\"audit_state\":1,\"role_info\":\"安全审核人员\",\"name\":\"wuqiongfang_dxm\",\"state\":\"1\",\"steps\":\"804\"},{\"role\":\"33\",\"audit_state\":1,\"role_info\":\"安全审核人员\",\"name\":\"zhangwei01_dxm\",\"state\":\"1\",\"steps\":\"804\"},{\"role\":\"33\",\"audit_state\":1,\"role_info\":\"安全审核人员\",\"name\":\"yangyang_dxm\",\"state\":\"1\",\"steps\":\"804\"}],\"process_state\":\"2\",\"release_type\":\"1\",\"task_id\":\"\"}"}}},"extra":null}